{
    "channel": {
        "title": "XML Historical Foreign Exchange Rates for Algerian Dinar (DZD) (9 May 2011)",
        "link": "http://www.floatrates.com/currency/dzd/",
        "xmlLink": "http://www.floatrates.com/daily/dzd.xml",
        "description": "XML historical foreign exchange rates for Algerian Dinar (DZD) from the Float Rates. Published at 9 May 2011.",
        "language": "en",
        "baseCurrency": "DZD",
        "pubDate": "Mon, 9 May 2011",
        "lastBuildDate": "Mon, 9 May 2011",
        "item": [
            {
                "title": "1 DZD = 0.013839 USD",
                "link": "http://www.floatrates.com/dzd/usd/",
                "description": "1 Algerian Dinar = 0.013839 U.S. Dollar",
                "pubDate": null,
                "baseCurrency": "DZD",
                "baseName": "Algerian Dinar",
                "targetCurrency": "USD",
                "targetName": "U.S. Dollar",
                "exchangeRate": "0.013839",
                "inverseRate": "72.257000",
                "inverseDescription": "1 U.S. Dollar = 72.257000 Algerian Dinar"
            },
            {
                "title": "1 DZD = 0.089908 CNY",
                "link": "http://www.floatrates.com/dzd/cny/",
                "description": "1 Algerian Dinar = 0.089908 Chinese Yuan",
                "pubDate": null,
                "baseCurrency": "DZD",
                "baseName": "Algerian Dinar",
                "targetCurrency": "CNY",
                "targetName": "Chinese Yuan",
                "exchangeRate": "0.089908",
                "inverseRate": "11.122502",
                "inverseDescription": "1 Chinese Yuan = 11.122502 Algerian Dinar"
            },
            {
                "title": "1 DZD = 1.116017 JPY",
                "link": "http://www.floatrates.com/dzd/jpy/",
                "description": "1 Algerian Dinar = 1.116017 Japanese Yen",
                "pubDate": null,
                "baseCurrency": "DZD",
                "baseName": "Algerian Dinar",
                "targetCurrency": "JPY",
                "targetName": "Japanese Yen",
                "exchangeRate": "1.116017",
                "inverseRate": "0.896044",
                "inverseDescription": "1 Japanese Yen = 0.896044 Algerian Dinar"
            },
            {
                "title": "1 DZD = 0.009617 EUR",
                "link": "http://www.floatrates.com/dzd/eur/",
                "description": "1 Algerian Dinar = 0.009617 Euro",
                "pubDate": null,
                "baseCurrency": "DZD",
                "baseName": "Algerian Dinar",
                "targetCurrency": "EUR",
                "targetName": "Euro",
                "exchangeRate": "0.009617",
                "inverseRate": "103.987475",
                "inverseDescription": "1 Euro = 103.987475 Algerian Dinar"
            },
            {
                "title": "1 DZD = 14.991585 KRW",
                "link": "http://www.floatrates.com/dzd/krw/",
                "description": "1 Algerian Dinar = 14.991585 South Korean Won",
                "pubDate": null,
                "baseCurrency": "DZD",
                "baseName": "Algerian Dinar",
                "targetCurrency": "KRW",
                "targetName": "South Korean Won",
                "exchangeRate": "14.991585",
                "inverseRate": "0.066704",
                "inverseDescription": "1 South Korean Won = 0.066704 Algerian Dinar"
            },
            {
                "title": "1 DZD = 0.008448 GBP",
                "link": "http://www.floatrates.com/dzd/gbp/",
                "description": "1 Algerian Dinar = 0.008448 U.K. Pound Sterling",
                "pubDate": null,
                "baseCurrency": "DZD",
                "baseName": "Algerian Dinar",
                "targetCurrency": "GBP",
                "targetName": "U.K. Pound Sterling",
                "exchangeRate": "0.008448",
                "inverseRate": "118.366137",
                "inverseDescription": "1 U.K. Pound Sterling = 118.366137 Algerian Dinar"
            },
            {
                "title": "1 DZD = 0.017048 SGD",
                "link": "http://www.floatrates.com/dzd/sgd/",
                "description": "1 Algerian Dinar = 0.017048 Singapore Dollar",
                "pubDate": null,
                "baseCurrency": "DZD",
                "baseName": "Algerian Dinar",
                "targetCurrency": "SGD",
                "targetName": "Singapore Dollar",
                "exchangeRate": "0.017048",
                "inverseRate": "58.659527",
                "inverseDescription": "1 Singapore Dollar = 58.659527 Algerian Dinar"
            },
            {
                "title": "1 DZD = 0.618533 INR",
                "link": "http://www.floatrates.com/dzd/inr/",
                "description": "1 Algerian Dinar = 0.618533 Indian Rupee",
                "pubDate": null,
                "baseCurrency": "DZD",
                "baseName": "Algerian Dinar",
                "targetCurrency": "INR",
                "targetName": "Indian Rupee",
                "exchangeRate": "0.618533",
                "inverseRate": "1.616728",
                "inverseDescription": "1 Indian Rupee = 1.616728 Algerian Dinar"
            },
            {
                "title": "1 DZD = 0.417922 THB",
                "link": "http://www.floatrates.com/dzd/thb/",
                "description": "1 Algerian Dinar = 0.417922 Thai Baht",
                "pubDate": null,
                "baseCurrency": "DZD",
                "baseName": "Algerian Dinar",
                "targetCurrency": "THB",
                "targetName": "Thai Baht",
                "exchangeRate": "0.417922",
                "inverseRate": "2.392793",
                "inverseDescription": "1 Thai Baht = 2.392793 Algerian Dinar"
            },
            {
                "title": "1 DZD = 0.017488 NZD",
                "link": "http://www.floatrates.com/dzd/nzd/",
                "description": "1 Algerian Dinar = 0.017488 New Zealand Dollar",
                "pubDate": null,
                "baseCurrency": "DZD",
                "baseName": "Algerian Dinar",
                "targetCurrency": "NZD",
                "targetName": "New Zealand Dollar",
                "exchangeRate": "0.017488",
                "inverseRate": "57.183513",
                "inverseDescription": "1 New Zealand Dollar = 57.183513 Algerian Dinar"
            },
            {
                "title": "1 DZD = 0.041366 MYR",
                "link": "http://www.floatrates.com/dzd/myr/",
                "description": "1 Algerian Dinar = 0.041366 Malaysian Ringgit",
                "pubDate": null,
                "baseCurrency": "DZD",
                "baseName": "Algerian Dinar",
                "targetCurrency": "MYR",
                "targetName": "Malaysian Ringgit",
                "exchangeRate": "0.041366",
                "inverseRate": "24.174401",
                "inverseDescription": "1 Malaysian Ringgit = 24.174401 Algerian Dinar"
            },
            {
                "title": "1 DZD = 118.384919 IDR",
                "link": "http://www.floatrates.com/dzd/idr/",
                "description": "1 Algerian Dinar = 118.384919 Indonesian Rupiah",
                "pubDate": null,
                "baseCurrency": "DZD",
                "baseName": "Algerian Dinar",
                "targetCurrency": "IDR",
                "targetName": "Indonesian Rupiah",
                "exchangeRate": "118.384919",
                "inverseRate": "0.008447",
                "inverseDescription": "1 Indonesian Rupiah = 0.008447 Algerian Dinar"
            },
            {
                "title": "1 DZD = 0.050826 AED",
                "link": "http://www.floatrates.com/dzd/aed/",
                "description": "1 Algerian Dinar = 0.050826 U.A.E Dirham",
                "pubDate": null,
                "baseCurrency": "DZD",
                "baseName": "Algerian Dinar",
                "targetCurrency": "AED",
                "targetName": "U.A.E Dirham",
                "exchangeRate": "0.050826",
                "inverseRate": "19.675105",
                "inverseDescription": "1 U.A.E Dirham = 19.675105 Algerian Dinar"
            },
            {
                "title": "1 DZD = 0.107558 HKD",
                "link": "http://www.floatrates.com/dzd/hkd/",
                "description": "1 Algerian Dinar = 0.107558 Hong Kong Dollar",
                "pubDate": null,
                "baseCurrency": "DZD",
                "baseName": "Algerian Dinar",
                "targetCurrency": "HKD",
                "targetName": "Hong Kong Dollar",
                "exchangeRate": "0.107558",
                "inverseRate": "9.297338",
                "inverseDescription": "1 Hong Kong Dollar = 9.297338 Algerian Dinar"
            },
            {
                "title": "1 DZD = 0.013326 CAD",
                "link": "http://www.floatrates.com/dzd/cad/",
                "description": "1 Algerian Dinar = 0.013326 Canadian Dollar",
                "pubDate": null,
                "baseCurrency": "DZD",
                "baseName": "Algerian Dinar",
                "targetCurrency": "CAD",
                "targetName": "Canadian Dollar",
                "exchangeRate": "0.013326",
                "inverseRate": "75.039302",
                "inverseDescription": "1 Canadian Dollar = 75.039302 Algerian Dinar"
            },
            {
                "title": "1 DZD = 0.092956 ZAR",
                "link": "http://www.floatrates.com/dzd/zar/",
                "description": "1 Algerian Dinar = 0.092956 South African Rand",
                "pubDate": null,
                "baseCurrency": "DZD",
                "baseName": "Algerian Dinar",
                "targetCurrency": "ZAR",
                "targetName": "South African Rand",
                "exchangeRate": "0.092956",
                "inverseRate": "10.757785",
                "inverseDescription": "1 South African Rand = 10.757785 Algerian Dinar"
            },
            {
                "title": "1 DZD = 0.012129 CHF",
                "link": "http://www.floatrates.com/dzd/chf/",
                "description": "1 Algerian Dinar = 0.012129 Swiss Franc",
                "pubDate": null,
                "baseCurrency": "DZD",
                "baseName": "Algerian Dinar",
                "targetCurrency": "CHF",
                "targetName": "Swiss Franc",
                "exchangeRate": "0.012129",
                "inverseRate": "82.447293",
                "inverseDescription": "1 Swiss Franc = 82.447293 Algerian Dinar"
            },
            {
                "title": "1 DZD = 0.086492 SEK",
                "link": "http://www.floatrates.com/dzd/sek/",
                "description": "1 Algerian Dinar = 0.086492 Swedish Krona",
                "pubDate": null,
                "baseCurrency": "DZD",
                "baseName": "Algerian Dinar",
                "targetCurrency": "SEK",
                "targetName": "Swedish Krona",
                "exchangeRate": "0.086492",
                "inverseRate": "11.561766",
                "inverseDescription": "1 Swedish Krona = 11.561766 Algerian Dinar"
            },
            {
                "title": "1 DZD = 0.012857 AUD",
                "link": "http://www.floatrates.com/dzd/aud/",
                "description": "1 Algerian Dinar = 0.012857 Australian Dollar",
                "pubDate": null,
                "baseCurrency": "DZD",
                "baseName": "Algerian Dinar",
                "targetCurrency": "AUD",
                "targetName": "Australian Dollar",
                "exchangeRate": "0.012857",
                "inverseRate": "77.778652",
                "inverseDescription": "1 Australian Dollar = 77.778652 Algerian Dinar"
            },
            {
                "title": "1 DZD = 1.000000 DZD",
                "link": "http://www.floatrates.com/dzd/dzd/",
                "description": "1 Algerian Dinar = 1.000000 Algerian Dinar",
                "pubDate": null,
                "baseCurrency": "DZD",
                "baseName": "Algerian Dinar",
                "targetCurrency": "DZD",
                "targetName": "Algerian Dinar",
                "exchangeRate": "1.000000",
                "inverseRate": "1.000000",
                "inverseDescription": "1 Algerian Dinar = 1.000000 Algerian Dinar"
            },
            {
                "title": "1 DZD = 0.089750 BWP",
                "link": "http://www.floatrates.com/dzd/bwp/",
                "description": "1 Algerian Dinar = 0.089750 Botswana Pula",
                "pubDate": null,
                "baseCurrency": "DZD",
                "baseName": "Algerian Dinar",
                "targetCurrency": "BWP",
                "targetName": "Botswana Pula",
                "exchangeRate": "0.089750",
                "inverseRate": "11.142029",
                "inverseDescription": "1 Botswana Pula = 11.142029 Algerian Dinar"
            },
            {
                "title": "1 DZD = 0.017034 BND",
                "link": "http://www.floatrates.com/dzd/bnd/",
                "description": "1 Algerian Dinar = 0.017034 Brunei Dollar",
                "pubDate": null,
                "baseCurrency": "DZD",
                "baseName": "Algerian Dinar",
                "targetCurrency": "BND",
                "targetName": "Brunei Dollar",
                "exchangeRate": "0.017034",
                "inverseRate": "58.707345",
                "inverseDescription": "1 Brunei Dollar = 58.707345 Algerian Dinar"
            },
            {
                "title": "1 DZD = 6.465394 CLP",
                "link": "http://www.floatrates.com/dzd/clp/",
                "description": "1 Algerian Dinar = 6.465394 Chilean Peso",
                "pubDate": null,
                "baseCurrency": "DZD",
                "baseName": "Algerian Dinar",
                "targetCurrency": "CLP",
                "targetName": "Chilean Peso",
                "exchangeRate": "6.465394",
                "inverseRate": "0.154670",
                "inverseDescription": "1 Chilean Peso = 0.154670 Algerian Dinar"
            },
            {
                "title": "1 DZD = 0.232422 CZK",
                "link": "http://www.floatrates.com/dzd/czk/",
                "description": "1 Algerian Dinar = 0.232422 Czech Koruna",
                "pubDate": null,
                "baseCurrency": "DZD",
                "baseName": "Algerian Dinar",
                "targetCurrency": "CZK",
                "targetName": "Czech Koruna",
                "exchangeRate": "0.232422",
                "inverseRate": "4.302515",
                "inverseDescription": "1 Czech Koruna = 4.302515 Algerian Dinar"
            },
            {
                "title": "1 DZD = 0.071683 DKK",
                "link": "http://www.floatrates.com/dzd/dkk/",
                "description": "1 Algerian Dinar = 0.071683 Danish Krone",
                "pubDate": null,
                "baseCurrency": "DZD",
                "baseName": "Algerian Dinar",
                "targetCurrency": "DKK",
                "targetName": "Danish Krone",
                "exchangeRate": "0.071683",
                "inverseRate": "13.950349",
                "inverseDescription": "1 Danish Krone = 13.950349 Algerian Dinar"
            },
            {
                "title": "1 DZD = 2.534976 HUF",
                "link": "http://www.floatrates.com/dzd/huf/",
                "description": "1 Algerian Dinar = 2.534976 Hungarian Forint",
                "pubDate": null,
                "baseCurrency": "DZD",
                "baseName": "Algerian Dinar",
                "targetCurrency": "HUF",
                "targetName": "Hungarian Forint",
                "exchangeRate": "2.534976",
                "inverseRate": "0.394481",
                "inverseDescription": "1 Hungarian Forint = 0.394481 Algerian Dinar"
            },
            {
                "title": "1 DZD = 1.576456 ISK",
                "link": "http://www.floatrates.com/dzd/isk/",
                "description": "1 Algerian Dinar = 1.576456 Icelandic Krona",
                "pubDate": null,
                "baseCurrency": "DZD",
                "baseName": "Algerian Dinar",
                "targetCurrency": "ISK",
                "targetName": "Icelandic Krona",
                "exchangeRate": "1.576456",
                "inverseRate": "0.634334",
                "inverseDescription": "1 Icelandic Krona = 0.634334 Algerian Dinar"
            },
            {
                "title": "1 DZD = 0.047705 ILS",
                "link": "http://www.floatrates.com/dzd/ils/",
                "description": "1 Algerian Dinar = 0.047705 Israeli New Sheqel",
                "pubDate": null,
                "baseCurrency": "DZD",
                "baseName": "Algerian Dinar",
                "targetCurrency": "ILS",
                "targetName": "Israeli New Sheqel",
                "exchangeRate": "0.047705",
                "inverseRate": "20.962239",
                "inverseDescription": "1 Israeli New Sheqel = 20.962239 Algerian Dinar"
            },
            {
                "title": "1 DZD = 2.016137 KZT",
                "link": "http://www.floatrates.com/dzd/kzt/",
                "description": "1 Algerian Dinar = 2.016137 Kazakhstani Tenge",
                "pubDate": null,
                "baseCurrency": "DZD",
                "baseName": "Algerian Dinar",
                "targetCurrency": "KZT",
                "targetName": "Kazakhstani Tenge",
                "exchangeRate": "2.016137",
                "inverseRate": "0.495998",
                "inverseDescription": "1 Kazakhstani Tenge = 0.495998 Algerian Dinar"
            },
            {
                "title": "1 DZD = 0.003806 KWD",
                "link": "http://www.floatrates.com/dzd/kwd/",
                "description": "1 Algerian Dinar = 0.003806 Kuwaiti Dinar",
                "pubDate": null,
                "baseCurrency": "DZD",
                "baseName": "Algerian Dinar",
                "targetCurrency": "KWD",
                "targetName": "Kuwaiti Dinar",
                "exchangeRate": "0.003806",
                "inverseRate": "262.752727",
                "inverseDescription": "1 Kuwaiti Dinar = 262.752727 Algerian Dinar"
            },
            {
                "title": "1 DZD = 0.026743 LYD",
                "link": "http://www.floatrates.com/dzd/lyd/",
                "description": "1 Algerian Dinar = 0.026743 Libyan Dinar",
                "pubDate": null,
                "baseCurrency": "DZD",
                "baseName": "Algerian Dinar",
                "targetCurrency": "LYD",
                "targetName": "Libyan Dinar",
                "exchangeRate": "0.026743",
                "inverseRate": "37.392362",
                "inverseDescription": "1 Libyan Dinar = 37.392362 Algerian Dinar"
            },
            {
                "title": "1 DZD = 0.377180 MUR",
                "link": "http://www.floatrates.com/dzd/mur/",
                "description": "1 Algerian Dinar = 0.377180 Mauritian Rupee",
                "pubDate": null,
                "baseCurrency": "DZD",
                "baseName": "Algerian Dinar",
                "targetCurrency": "MUR",
                "targetName": "Mauritian Rupee",
                "exchangeRate": "0.377180",
                "inverseRate": "2.651254",
                "inverseDescription": "1 Mauritian Rupee = 2.651254 Algerian Dinar"
            },
            {
                "title": "1 DZD = 0.991599 NPR",
                "link": "http://www.floatrates.com/dzd/npr/",
                "description": "1 Algerian Dinar = 0.991599 Nepalese Rupee",
                "pubDate": null,
                "baseCurrency": "DZD",
                "baseName": "Algerian Dinar",
                "targetCurrency": "NPR",
                "targetName": "Nepalese Rupee",
                "exchangeRate": "0.991599",
                "inverseRate": "1.008472",
                "inverseDescription": "1 Nepalese Rupee = 1.008472 Algerian Dinar"
            },
            {
                "title": "1 DZD = 0.005321 OMR",
                "link": "http://www.floatrates.com/dzd/omr/",
                "description": "1 Algerian Dinar = 0.005321 Omani Rial",
                "pubDate": null,
                "baseCurrency": "DZD",
                "baseName": "Algerian Dinar",
                "targetCurrency": "OMR",
                "targetName": "Omani Rial",
                "exchangeRate": "0.005321",
                "inverseRate": "187.924577",
                "inverseDescription": "1 Omani Rial = 187.924577 Algerian Dinar"
            },
            {
                "title": "1 DZD = 1.179623 PKR",
                "link": "http://www.floatrates.com/dzd/pkr/",
                "description": "1 Algerian Dinar = 1.179623 Pakistani Rupee",
                "pubDate": null,
                "baseCurrency": "DZD",
                "baseName": "Algerian Dinar",
                "targetCurrency": "PKR",
                "targetName": "Pakistani Rupee",
                "exchangeRate": "1.179623",
                "inverseRate": "0.847729",
                "inverseDescription": "1 Pakistani Rupee = 0.847729 Algerian Dinar"
            },
            {
                "title": "1 DZD = 0.037706 PLN",
                "link": "http://www.floatrates.com/dzd/pln/",
                "description": "1 Algerian Dinar = 0.037706 Polish Zloty",
                "pubDate": null,
                "baseCurrency": "DZD",
                "baseName": "Algerian Dinar",
                "targetCurrency": "PLN",
                "targetName": "Polish Zloty",
                "exchangeRate": "0.037706",
                "inverseRate": "26.521195",
                "inverseDescription": "1 Polish Zloty = 26.521195 Algerian Dinar"
            },
            {
                "title": "1 DZD = 0.050376 QAR",
                "link": "http://www.floatrates.com/dzd/qar/",
                "description": "1 Algerian Dinar = 0.050376 Qatari Rial",
                "pubDate": null,
                "baseCurrency": "DZD",
                "baseName": "Algerian Dinar",
                "targetCurrency": "QAR",
                "targetName": "Qatari Rial",
                "exchangeRate": "0.050376",
                "inverseRate": "19.850824",
                "inverseDescription": "1 Qatari Rial = 19.850824 Algerian Dinar"
            },
            {
                "title": "1 DZD = 0.051898 SAR",
                "link": "http://www.floatrates.com/dzd/sar/",
                "description": "1 Algerian Dinar = 0.051898 Saudi Riyal",
                "pubDate": null,
                "baseCurrency": "DZD",
                "baseName": "Algerian Dinar",
                "targetCurrency": "SAR",
                "targetName": "Saudi Riyal",
                "exchangeRate": "0.051898",
                "inverseRate": "19.268533",
                "inverseDescription": "1 Saudi Riyal = 19.268533 Algerian Dinar"
            },
            {
                "title": "1 DZD = 1.519516 LKR",
                "link": "http://www.floatrates.com/dzd/lkr/",
                "description": "1 Algerian Dinar = 1.519516 Sri Lanka Rupee",
                "pubDate": null,
                "baseCurrency": "DZD",
                "baseName": "Algerian Dinar",
                "targetCurrency": "LKR",
                "targetName": "Sri Lanka Rupee",
                "exchangeRate": "1.519516",
                "inverseRate": "0.658104",
                "inverseDescription": "1 Sri Lanka Rupee = 0.658104 Algerian Dinar"
            },
            {
                "title": "1 DZD = 0.088577 TTD",
                "link": "http://www.floatrates.com/dzd/ttd/",
                "description": "1 Algerian Dinar = 0.088577 Trinidad Tobago Dollar",
                "pubDate": null,
                "baseCurrency": "DZD",
                "baseName": "Algerian Dinar",
                "targetCurrency": "TTD",
                "targetName": "Trinidad Tobago Dollar",
                "exchangeRate": "0.088577",
                "inverseRate": "11.289627",
                "inverseDescription": "1 Trinidad Tobago Dollar = 11.289627 Algerian Dinar"
            },
            {
                "title": "1 DZD = 0.018660 TND",
                "link": "http://www.floatrates.com/dzd/tnd/",
                "description": "1 Algerian Dinar = 0.018660 Tunisian Dinar",
                "pubDate": null,
                "baseCurrency": "DZD",
                "baseName": "Algerian Dinar",
                "targetCurrency": "TND",
                "targetName": "Tunisian Dinar",
                "exchangeRate": "0.018660",
                "inverseRate": "53.591189",
                "inverseDescription": "1 Tunisian Dinar = 53.591189 Algerian Dinar"
            },
            {
                "title": "1 DZD = 0.059362 VEF",
                "link": "http://www.floatrates.com/dzd/vef/",
                "description": "1 Algerian Dinar = 0.059362 Venezuelan Bolivar (till 20 August 2018)",
                "pubDate": null,
                "baseCurrency": "DZD",
                "baseName": "Algerian Dinar",
                "targetCurrency": "VEF",
                "targetName": "Venezuelan Bolivar (till 20 August 2018)",
                "exchangeRate": "0.059362",
                "inverseRate": "16.845872",
                "inverseDescription": "1 Venezuelan Bolivar (till 20 August 2018) = 16.845872 Algerian Dinar"
            },
            {
                "title": "1 DZD = 0.018801 BGN",
                "link": "http://www.floatrates.com/dzd/bgn/",
                "description": "1 Algerian Dinar = 0.018801 Bulgarian Lev",
                "pubDate": null,
                "baseCurrency": "DZD",
                "baseName": "Algerian Dinar",
                "targetCurrency": "BGN",
                "targetName": "Bulgarian Lev",
                "exchangeRate": "0.018801",
                "inverseRate": "53.189694",
                "inverseDescription": "1 Bulgarian Lev = 53.189694 Algerian Dinar"
            },
            {
                "title": "1 DZD = 0.033191 LTL",
                "link": "http://www.floatrates.com/dzd/ltl/",
                "description": "1 Algerian Dinar = 0.033191 Lithuanian Litas",
                "pubDate": null,
                "baseCurrency": "DZD",
                "baseName": "Algerian Dinar",
                "targetCurrency": "LTL",
                "targetName": "Lithuanian Litas",
                "exchangeRate": "0.033191",
                "inverseRate": "30.128708",
                "inverseDescription": "1 Lithuanian Litas = 30.128708 Algerian Dinar"
            },
            {
                "title": "1 DZD = 0.006818 LVL",
                "link": "http://www.floatrates.com/dzd/lvl/",
                "description": "1 Algerian Dinar = 0.006818 Latvian Lats",
                "pubDate": null,
                "baseCurrency": "DZD",
                "baseName": "Algerian Dinar",
                "targetCurrency": "LVL",
                "targetName": "Latvian Lats",
                "exchangeRate": "0.006818",
                "inverseRate": "146.663475",
                "inverseDescription": "1 Latvian Lats = 146.663475 Algerian Dinar"
            },
            {
                "title": "1 DZD = 0.039410 RON",
                "link": "http://www.floatrates.com/dzd/ron/",
                "description": "1 Algerian Dinar = 0.039410 Romanian New Leu",
                "pubDate": null,
                "baseCurrency": "DZD",
                "baseName": "Algerian Dinar",
                "targetCurrency": "RON",
                "targetName": "Romanian New Leu",
                "exchangeRate": "0.039410",
                "inverseRate": "25.374019",
                "inverseDescription": "1 Romanian New Leu = 25.374019 Algerian Dinar"
            },
            {
                "title": "1 DZD = 0.075619 NOK",
                "link": "http://www.floatrates.com/dzd/nok/",
                "description": "1 Algerian Dinar = 0.075619 Norwegian Krone",
                "pubDate": null,
                "baseCurrency": "DZD",
                "baseName": "Algerian Dinar",
                "targetCurrency": "NOK",
                "targetName": "Norwegian Krone",
                "exchangeRate": "0.075619",
                "inverseRate": "13.224230",
                "inverseDescription": "1 Norwegian Krone = 13.224230 Algerian Dinar"
            },
            {
                "title": "1 DZD = 0.384126 RUB",
                "link": "http://www.floatrates.com/dzd/rub/",
                "description": "1 Algerian Dinar = 0.384126 Russian Rouble",
                "pubDate": null,
                "baseCurrency": "DZD",
                "baseName": "Algerian Dinar",
                "targetCurrency": "RUB",
                "targetName": "Russian Rouble",
                "exchangeRate": "0.384126",
                "inverseRate": "2.603313",
                "inverseDescription": "1 Russian Rouble = 2.603313 Algerian Dinar"
            },
            {
                "title": "1 DZD = 0.021342 TRY",
                "link": "http://www.floatrates.com/dzd/try/",
                "description": "1 Algerian Dinar = 0.021342 Turkish Lira",
                "pubDate": null,
                "baseCurrency": "DZD",
                "baseName": "Algerian Dinar",
                "targetCurrency": "TRY",
                "targetName": "Turkish Lira",
                "exchangeRate": "0.021342",
                "inverseRate": "46.855420",
                "inverseDescription": "1 Turkish Lira = 46.855420 Algerian Dinar"
            },
            {
                "title": "1 DZD = 0.022270 BRL",
                "link": "http://www.floatrates.com/dzd/brl/",
                "description": "1 Algerian Dinar = 0.022270 Brazilian Real",
                "pubDate": null,
                "baseCurrency": "DZD",
                "baseName": "Algerian Dinar",
                "targetCurrency": "BRL",
                "targetName": "Brazilian Real",
                "exchangeRate": "0.022270",
                "inverseRate": "44.903700",
                "inverseDescription": "1 Brazilian Real = 44.903700 Algerian Dinar"
            },
            {
                "title": "1 DZD = 0.160607 MXN",
                "link": "http://www.floatrates.com/dzd/mxn/",
                "description": "1 Algerian Dinar = 0.160607 Mexican Peso",
                "pubDate": null,
                "baseCurrency": "DZD",
                "baseName": "Algerian Dinar",
                "targetCurrency": "MXN",
                "targetName": "Mexican Peso",
                "exchangeRate": "0.160607",
                "inverseRate": "6.226375",
                "inverseDescription": "1 Mexican Peso = 6.226375 Algerian Dinar"
            },
            {
                "title": "1 DZD = 0.594953 PHP",
                "link": "http://www.floatrates.com/dzd/php/",
                "description": "1 Algerian Dinar = 0.594953 Philippine Peso",
                "pubDate": null,
                "baseCurrency": "DZD",
                "baseName": "Algerian Dinar",
                "targetCurrency": "PHP",
                "targetName": "Philippine Peso",
                "exchangeRate": "0.594953",
                "inverseRate": "1.680805",
                "inverseDescription": "1 Philippine Peso = 1.680805 Algerian Dinar"
            },
            {
                "title": "1 DZD = 24.488423 COP",
                "link": "http://www.floatrates.com/dzd/cop/",
                "description": "1 Algerian Dinar = 24.488423 Colombian Peso",
                "pubDate": null,
                "baseCurrency": "DZD",
                "baseName": "Algerian Dinar",
                "targetCurrency": "COP",
                "targetName": "Colombian Peso",
                "exchangeRate": "24.488423",
                "inverseRate": "0.040836",
                "inverseDescription": "1 Colombian Peso = 0.040836 Algerian Dinar"
            },
            {
                "title": "1 DZD = 0.068644 HRK",
                "link": "http://www.floatrates.com/dzd/hrk/",
                "description": "1 Algerian Dinar = 0.068644 Croatian Kuna",
                "pubDate": null,
                "baseCurrency": "DZD",
                "baseName": "Algerian Dinar",
                "targetCurrency": "HRK",
                "targetName": "Croatian Kuna",
                "exchangeRate": "0.068644",
                "inverseRate": "14.567888",
                "inverseDescription": "1 Croatian Kuna = 14.567888 Algerian Dinar"
            }
        ]
    }
}