{
    "channel": {
        "title": "XML Historical Foreign Exchange Rates for Japanese Yen (JPY) (30 May 2011)",
        "link": "http://www.floatrates.com/currency/jpy/",
        "xmlLink": "http://www.floatrates.com/daily/jpy.xml",
        "description": "XML historical foreign exchange rates for Japanese Yen (JPY) from the Float Rates. Published at 30 May 2011.",
        "language": "en",
        "baseCurrency": "JPY",
        "pubDate": "Mon, 30 May 2011",
        "lastBuildDate": "Mon, 30 May 2011",
        "item": [
            {
                "title": "1 JPY = 0.012366 USD",
                "link": "http://www.floatrates.com/jpy/usd/",
                "description": "1 Japanese Yen = 0.012366 U.S. Dollar",
                "pubDate": null,
                "baseCurrency": "JPY",
                "baseName": "Japanese Yen",
                "targetCurrency": "USD",
                "targetName": "U.S. Dollar",
                "exchangeRate": "0.012366",
                "inverseRate": "80.864939",
                "inverseDescription": "1 U.S. Dollar = 80.864939 Japanese Yen"
            },
            {
                "title": "1 JPY = 0.080202 CNY",
                "link": "http://www.floatrates.com/jpy/cny/",
                "description": "1 Japanese Yen = 0.080202 Chinese Yuan",
                "pubDate": null,
                "baseCurrency": "JPY",
                "baseName": "Japanese Yen",
                "targetCurrency": "CNY",
                "targetName": "Chinese Yuan",
                "exchangeRate": "0.080202",
                "inverseRate": "12.468526",
                "inverseDescription": "1 Chinese Yuan = 12.468526 Japanese Yen"
            },
            {
                "title": "1 JPY = 1.000000 JPY",
                "link": "http://www.floatrates.com/jpy/jpy/",
                "description": "1 Japanese Yen = 1.000000 Japanese Yen",
                "pubDate": null,
                "baseCurrency": "JPY",
                "baseName": "Japanese Yen",
                "targetCurrency": "JPY",
                "targetName": "Japanese Yen",
                "exchangeRate": "1.000000",
                "inverseRate": "1.000000",
                "inverseDescription": "1 Japanese Yen = 1.000000 Japanese Yen"
            },
            {
                "title": "1 JPY = 0.008664 EUR",
                "link": "http://www.floatrates.com/jpy/eur/",
                "description": "1 Japanese Yen = 0.008664 Euro",
                "pubDate": null,
                "baseCurrency": "JPY",
                "baseName": "Japanese Yen",
                "targetCurrency": "EUR",
                "targetName": "Euro",
                "exchangeRate": "0.008664",
                "inverseRate": "115.424129",
                "inverseDescription": "1 Euro = 115.424129 Japanese Yen"
            },
            {
                "title": "1 JPY = 13.355790 KRW",
                "link": "http://www.floatrates.com/jpy/krw/",
                "description": "1 Japanese Yen = 13.355790 South Korean Won",
                "pubDate": null,
                "baseCurrency": "JPY",
                "baseName": "Japanese Yen",
                "targetCurrency": "KRW",
                "targetName": "South Korean Won",
                "exchangeRate": "13.355790",
                "inverseRate": "0.074874",
                "inverseDescription": "1 South Korean Won = 0.074874 Japanese Yen"
            },
            {
                "title": "1 JPY = 0.007508 GBP",
                "link": "http://www.floatrates.com/jpy/gbp/",
                "description": "1 Japanese Yen = 0.007508 U.K. Pound Sterling",
                "pubDate": null,
                "baseCurrency": "JPY",
                "baseName": "Japanese Yen",
                "targetCurrency": "GBP",
                "targetName": "U.K. Pound Sterling",
                "exchangeRate": "0.007508",
                "inverseRate": "133.184688",
                "inverseDescription": "1 U.K. Pound Sterling = 133.184688 Japanese Yen"
            },
            {
                "title": "1 JPY = 0.015271 SGD",
                "link": "http://www.floatrates.com/jpy/sgd/",
                "description": "1 Japanese Yen = 0.015271 Singapore Dollar",
                "pubDate": null,
                "baseCurrency": "JPY",
                "baseName": "Japanese Yen",
                "targetCurrency": "SGD",
                "targetName": "Singapore Dollar",
                "exchangeRate": "0.015271",
                "inverseRate": "65.483860",
                "inverseDescription": "1 Singapore Dollar = 65.483860 Japanese Yen"
            },
            {
                "title": "1 JPY = 0.557818 INR",
                "link": "http://www.floatrates.com/jpy/inr/",
                "description": "1 Japanese Yen = 0.557818 Indian Rupee",
                "pubDate": null,
                "baseCurrency": "JPY",
                "baseName": "Japanese Yen",
                "targetCurrency": "INR",
                "targetName": "Indian Rupee",
                "exchangeRate": "0.557818",
                "inverseRate": "1.792700",
                "inverseDescription": "1 Indian Rupee = 1.792700 Japanese Yen"
            },
            {
                "title": "1 JPY = 0.375234 THB",
                "link": "http://www.floatrates.com/jpy/thb/",
                "description": "1 Japanese Yen = 0.375234 Thai Baht",
                "pubDate": null,
                "baseCurrency": "JPY",
                "baseName": "Japanese Yen",
                "targetCurrency": "THB",
                "targetName": "Thai Baht",
                "exchangeRate": "0.375234",
                "inverseRate": "2.665002",
                "inverseDescription": "1 Thai Baht = 2.665002 Japanese Yen"
            },
            {
                "title": "1 JPY = 0.015138 NZD",
                "link": "http://www.floatrates.com/jpy/nzd/",
                "description": "1 Japanese Yen = 0.015138 New Zealand Dollar",
                "pubDate": null,
                "baseCurrency": "JPY",
                "baseName": "Japanese Yen",
                "targetCurrency": "NZD",
                "targetName": "New Zealand Dollar",
                "exchangeRate": "0.015138",
                "inverseRate": "66.060782",
                "inverseDescription": "1 New Zealand Dollar = 66.060782 Japanese Yen"
            },
            {
                "title": "1 JPY = 0.356304 TWD",
                "link": "http://www.floatrates.com/jpy/twd/",
                "description": "1 Japanese Yen = 0.356304 New Taiwan Dollar",
                "pubDate": null,
                "baseCurrency": "JPY",
                "baseName": "Japanese Yen",
                "targetCurrency": "TWD",
                "targetName": "New Taiwan Dollar",
                "exchangeRate": "0.356304",
                "inverseRate": "2.806589",
                "inverseDescription": "1 New Taiwan Dollar  = 2.806589 Japanese Yen"
            },
            {
                "title": "1 JPY = 0.037340 MYR",
                "link": "http://www.floatrates.com/jpy/myr/",
                "description": "1 Japanese Yen = 0.037340 Malaysian Ringgit",
                "pubDate": null,
                "baseCurrency": "JPY",
                "baseName": "Japanese Yen",
                "targetCurrency": "MYR",
                "targetName": "Malaysian Ringgit",
                "exchangeRate": "0.037340",
                "inverseRate": "26.780644",
                "inverseDescription": "1 Malaysian Ringgit = 26.780644 Japanese Yen"
            },
            {
                "title": "1 JPY = 105.720080 IDR",
                "link": "http://www.floatrates.com/jpy/idr/",
                "description": "1 Japanese Yen = 105.720080 Indonesian Rupiah",
                "pubDate": null,
                "baseCurrency": "JPY",
                "baseName": "Japanese Yen",
                "targetCurrency": "IDR",
                "targetName": "Indonesian Rupiah",
                "exchangeRate": "105.720080",
                "inverseRate": "0.009459",
                "inverseDescription": "1 Indonesian Rupiah = 0.009459 Japanese Yen"
            },
            {
                "title": "1 JPY = 0.045429 AED",
                "link": "http://www.floatrates.com/jpy/aed/",
                "description": "1 Japanese Yen = 0.045429 U.A.E Dirham",
                "pubDate": null,
                "baseCurrency": "JPY",
                "baseName": "Japanese Yen",
                "targetCurrency": "AED",
                "targetName": "U.A.E Dirham",
                "exchangeRate": "0.045429",
                "inverseRate": "22.012212",
                "inverseDescription": "1 U.A.E Dirham = 22.012212 Japanese Yen"
            },
            {
                "title": "1 JPY = 0.096201 HKD",
                "link": "http://www.floatrates.com/jpy/hkd/",
                "description": "1 Japanese Yen = 0.096201 Hong Kong Dollar",
                "pubDate": null,
                "baseCurrency": "JPY",
                "baseName": "Japanese Yen",
                "targetCurrency": "HKD",
                "targetName": "Hong Kong Dollar",
                "exchangeRate": "0.096201",
                "inverseRate": "10.394915",
                "inverseDescription": "1 Hong Kong Dollar = 10.394915 Japanese Yen"
            },
            {
                "title": "1 JPY = 0.012072 CAD",
                "link": "http://www.floatrates.com/jpy/cad/",
                "description": "1 Japanese Yen = 0.012072 Canadian Dollar",
                "pubDate": null,
                "baseCurrency": "JPY",
                "baseName": "Japanese Yen",
                "targetCurrency": "CAD",
                "targetName": "Canadian Dollar",
                "exchangeRate": "0.012072",
                "inverseRate": "82.835060",
                "inverseDescription": "1 Canadian Dollar = 82.835060 Japanese Yen"
            },
            {
                "title": "1 JPY = 0.085709 ZAR",
                "link": "http://www.floatrates.com/jpy/zar/",
                "description": "1 Japanese Yen = 0.085709 South African Rand",
                "pubDate": null,
                "baseCurrency": "JPY",
                "baseName": "Japanese Yen",
                "targetCurrency": "ZAR",
                "targetName": "South African Rand",
                "exchangeRate": "0.085709",
                "inverseRate": "11.667363",
                "inverseDescription": "1 South African Rand = 11.667363 Japanese Yen"
            },
            {
                "title": "1 JPY = 0.010539 CHF",
                "link": "http://www.floatrates.com/jpy/chf/",
                "description": "1 Japanese Yen = 0.010539 Swiss Franc",
                "pubDate": null,
                "baseCurrency": "JPY",
                "baseName": "Japanese Yen",
                "targetCurrency": "CHF",
                "targetName": "Swiss Franc",
                "exchangeRate": "0.010539",
                "inverseRate": "94.885526",
                "inverseDescription": "1 Swiss Franc = 94.885526 Japanese Yen"
            },
            {
                "title": "1 JPY = 0.077081 SEK",
                "link": "http://www.floatrates.com/jpy/sek/",
                "description": "1 Japanese Yen = 0.077081 Swedish Krona",
                "pubDate": null,
                "baseCurrency": "JPY",
                "baseName": "Japanese Yen",
                "targetCurrency": "SEK",
                "targetName": "Swedish Krona",
                "exchangeRate": "0.077081",
                "inverseRate": "12.973448",
                "inverseDescription": "1 Swedish Krona = 12.973448 Japanese Yen"
            },
            {
                "title": "1 JPY = 0.011574 AUD",
                "link": "http://www.floatrates.com/jpy/aud/",
                "description": "1 Japanese Yen = 0.011574 Australian Dollar",
                "pubDate": null,
                "baseCurrency": "JPY",
                "baseName": "Japanese Yen",
                "targetCurrency": "AUD",
                "targetName": "Australian Dollar",
                "exchangeRate": "0.011574",
                "inverseRate": "86.402906",
                "inverseDescription": "1 Australian Dollar = 86.402906 Japanese Yen"
            },
            {
                "title": "1 JPY = 0.016946 BGN",
                "link": "http://www.floatrates.com/jpy/bgn/",
                "description": "1 Japanese Yen = 0.016946 Bulgarian Lev",
                "pubDate": null,
                "baseCurrency": "JPY",
                "baseName": "Japanese Yen",
                "targetCurrency": "BGN",
                "targetName": "Bulgarian Lev",
                "exchangeRate": "0.016946",
                "inverseRate": "59.009327",
                "inverseDescription": "1 Bulgarian Lev = 59.009327 Japanese Yen"
            },
            {
                "title": "1 JPY = 0.212240 CZK",
                "link": "http://www.floatrates.com/jpy/czk/",
                "description": "1 Japanese Yen = 0.212240 Czech Koruna",
                "pubDate": null,
                "baseCurrency": "JPY",
                "baseName": "Japanese Yen",
                "targetCurrency": "CZK",
                "targetName": "Czech Koruna",
                "exchangeRate": "0.212240",
                "inverseRate": "4.711640",
                "inverseDescription": "1 Czech Koruna = 4.711640 Japanese Yen"
            },
            {
                "title": "1 JPY = 0.064567 DKK",
                "link": "http://www.floatrates.com/jpy/dkk/",
                "description": "1 Japanese Yen = 0.064567 Danish Krone",
                "pubDate": null,
                "baseCurrency": "JPY",
                "baseName": "Japanese Yen",
                "targetCurrency": "DKK",
                "targetName": "Danish Krone",
                "exchangeRate": "0.064567",
                "inverseRate": "15.487678",
                "inverseDescription": "1 Danish Krone = 15.487678 Japanese Yen"
            },
            {
                "title": "1 JPY = 2.325810 HUF",
                "link": "http://www.floatrates.com/jpy/huf/",
                "description": "1 Japanese Yen = 2.325810 Hungarian Forint",
                "pubDate": null,
                "baseCurrency": "JPY",
                "baseName": "Japanese Yen",
                "targetCurrency": "HUF",
                "targetName": "Hungarian Forint",
                "exchangeRate": "2.325810",
                "inverseRate": "0.429958",
                "inverseDescription": "1 Hungarian Forint = 0.429958 Japanese Yen"
            },
            {
                "title": "1 JPY = 0.029918 LTL",
                "link": "http://www.floatrates.com/jpy/ltl/",
                "description": "1 Japanese Yen = 0.029918 Lithuanian Litas",
                "pubDate": null,
                "baseCurrency": "JPY",
                "baseName": "Japanese Yen",
                "targetCurrency": "LTL",
                "targetName": "Lithuanian Litas",
                "exchangeRate": "0.029918",
                "inverseRate": "33.425174",
                "inverseDescription": "1 Lithuanian Litas = 33.425174 Japanese Yen"
            },
            {
                "title": "1 JPY = 0.006148 LVL",
                "link": "http://www.floatrates.com/jpy/lvl/",
                "description": "1 Japanese Yen = 0.006148 Latvian Lats",
                "pubDate": null,
                "baseCurrency": "JPY",
                "baseName": "Japanese Yen",
                "targetCurrency": "LVL",
                "targetName": "Latvian Lats",
                "exchangeRate": "0.006148",
                "inverseRate": "162.664470",
                "inverseDescription": "1 Latvian Lats = 162.664470 Japanese Yen"
            },
            {
                "title": "1 JPY = 0.034464 PLN",
                "link": "http://www.floatrates.com/jpy/pln/",
                "description": "1 Japanese Yen = 0.034464 Polish Zloty",
                "pubDate": null,
                "baseCurrency": "JPY",
                "baseName": "Japanese Yen",
                "targetCurrency": "PLN",
                "targetName": "Polish Zloty",
                "exchangeRate": "0.034464",
                "inverseRate": "29.015389",
                "inverseDescription": "1 Polish Zloty = 29.015389 Japanese Yen"
            },
            {
                "title": "1 JPY = 0.035750 RON",
                "link": "http://www.floatrates.com/jpy/ron/",
                "description": "1 Japanese Yen = 0.035750 Romanian New Leu",
                "pubDate": null,
                "baseCurrency": "JPY",
                "baseName": "Japanese Yen",
                "targetCurrency": "RON",
                "targetName": "Romanian New Leu",
                "exchangeRate": "0.035750",
                "inverseRate": "27.971637",
                "inverseDescription": "1 Romanian New Leu = 27.971637 Japanese Yen"
            },
            {
                "title": "1 JPY = 0.067158 NOK",
                "link": "http://www.floatrates.com/jpy/nok/",
                "description": "1 Japanese Yen = 0.067158 Norwegian Krone",
                "pubDate": null,
                "baseCurrency": "JPY",
                "baseName": "Japanese Yen",
                "targetCurrency": "NOK",
                "targetName": "Norwegian Krone",
                "exchangeRate": "0.067158",
                "inverseRate": "14.890273",
                "inverseDescription": "1 Norwegian Krone = 14.890273 Japanese Yen"
            },
            {
                "title": "1 JPY = 0.064540 HRK",
                "link": "http://www.floatrates.com/jpy/hrk/",
                "description": "1 Japanese Yen = 0.064540 Croatian Kuna",
                "pubDate": null,
                "baseCurrency": "JPY",
                "baseName": "Japanese Yen",
                "targetCurrency": "HRK",
                "targetName": "Croatian Kuna",
                "exchangeRate": "0.064540",
                "inverseRate": "15.494263",
                "inverseDescription": "1 Croatian Kuna = 15.494263 Japanese Yen"
            },
            {
                "title": "1 JPY = 0.347446 RUB",
                "link": "http://www.floatrates.com/jpy/rub/",
                "description": "1 Japanese Yen = 0.347446 Russian Rouble",
                "pubDate": null,
                "baseCurrency": "JPY",
                "baseName": "Japanese Yen",
                "targetCurrency": "RUB",
                "targetName": "Russian Rouble",
                "exchangeRate": "0.347446",
                "inverseRate": "2.878147",
                "inverseDescription": "1 Russian Rouble = 2.878147 Japanese Yen"
            },
            {
                "title": "1 JPY = 0.019819 TRY",
                "link": "http://www.floatrates.com/jpy/try/",
                "description": "1 Japanese Yen = 0.019819 Turkish Lira",
                "pubDate": null,
                "baseCurrency": "JPY",
                "baseName": "Japanese Yen",
                "targetCurrency": "TRY",
                "targetName": "Turkish Lira",
                "exchangeRate": "0.019819",
                "inverseRate": "50.457519",
                "inverseDescription": "1 Turkish Lira = 50.457519 Japanese Yen"
            },
            {
                "title": "1 JPY = 0.019737 BRL",
                "link": "http://www.floatrates.com/jpy/brl/",
                "description": "1 Japanese Yen = 0.019737 Brazilian Real",
                "pubDate": null,
                "baseCurrency": "JPY",
                "baseName": "Japanese Yen",
                "targetCurrency": "BRL",
                "targetName": "Brazilian Real",
                "exchangeRate": "0.019737",
                "inverseRate": "50.666896",
                "inverseDescription": "1 Brazilian Real = 50.666896 Japanese Yen"
            },
            {
                "title": "1 JPY = 0.042693 ILS",
                "link": "http://www.floatrates.com/jpy/ils/",
                "description": "1 Japanese Yen = 0.042693 Israeli New Sheqel",
                "pubDate": null,
                "baseCurrency": "JPY",
                "baseName": "Japanese Yen",
                "targetCurrency": "ILS",
                "targetName": "Israeli New Sheqel",
                "exchangeRate": "0.042693",
                "inverseRate": "23.422995",
                "inverseDescription": "1 Israeli New Sheqel = 23.422995 Japanese Yen"
            },
            {
                "title": "1 JPY = 0.143627 MXN",
                "link": "http://www.floatrates.com/jpy/mxn/",
                "description": "1 Japanese Yen = 0.143627 Mexican Peso",
                "pubDate": null,
                "baseCurrency": "JPY",
                "baseName": "Japanese Yen",
                "targetCurrency": "MXN",
                "targetName": "Mexican Peso",
                "exchangeRate": "0.143627",
                "inverseRate": "6.962465",
                "inverseDescription": "1 Mexican Peso = 6.962465 Japanese Yen"
            },
            {
                "title": "1 JPY = 0.535985 PHP",
                "link": "http://www.floatrates.com/jpy/php/",
                "description": "1 Japanese Yen = 0.535985 Philippine Peso",
                "pubDate": null,
                "baseCurrency": "JPY",
                "baseName": "Japanese Yen",
                "targetCurrency": "PHP",
                "targetName": "Philippine Peso",
                "exchangeRate": "0.535985",
                "inverseRate": "1.865725",
                "inverseDescription": "1 Philippine Peso = 1.865725 Japanese Yen"
            },
            {
                "title": "1 JPY = 0.053562 ARS",
                "link": "http://www.floatrates.com/jpy/ars/",
                "description": "1 Japanese Yen = 0.053562 Argentine Peso",
                "pubDate": null,
                "baseCurrency": "JPY",
                "baseName": "Japanese Yen",
                "targetCurrency": "ARS",
                "targetName": "Argentine Peso",
                "exchangeRate": "0.053562",
                "inverseRate": "18.670121",
                "inverseDescription": "1 Argentine Peso = 18.670121 Japanese Yen"
            },
            {
                "title": "1 JPY = 0.012375 BSD",
                "link": "http://www.floatrates.com/jpy/bsd/",
                "description": "1 Japanese Yen = 0.012375 Bahamian Dollar",
                "pubDate": null,
                "baseCurrency": "JPY",
                "baseName": "Japanese Yen",
                "targetCurrency": "BSD",
                "targetName": "Bahamian Dollar",
                "exchangeRate": "0.012375",
                "inverseRate": "80.809666",
                "inverseDescription": "1 Bahamian Dollar = 80.809666 Japanese Yen"
            },
            {
                "title": "1 JPY = 5.689051 XAF",
                "link": "http://www.floatrates.com/jpy/xaf/",
                "description": "1 Japanese Yen = 5.689051 Central African CFA Franc",
                "pubDate": null,
                "baseCurrency": "JPY",
                "baseName": "Japanese Yen",
                "targetCurrency": "XAF",
                "targetName": "Central African CFA Franc",
                "exchangeRate": "5.689051",
                "inverseRate": "0.175776",
                "inverseDescription": "1 Central African CFA Franc = 0.175776 Japanese Yen"
            },
            {
                "title": "1 JPY = 1.034550 XPF",
                "link": "http://www.floatrates.com/jpy/xpf/",
                "description": "1 Japanese Yen = 1.034550 CFP Franc",
                "pubDate": null,
                "baseCurrency": "JPY",
                "baseName": "Japanese Yen",
                "targetCurrency": "XPF",
                "targetName": "CFP Franc",
                "exchangeRate": "1.034550",
                "inverseRate": "0.966604",
                "inverseDescription": "1 CFP Franc = 0.966604 Japanese Yen"
            },
            {
                "title": "1 JPY = 5.776073 CLP",
                "link": "http://www.floatrates.com/jpy/clp/",
                "description": "1 Japanese Yen = 5.776073 Chilean Peso",
                "pubDate": null,
                "baseCurrency": "JPY",
                "baseName": "Japanese Yen",
                "targetCurrency": "CLP",
                "targetName": "Chilean Peso",
                "exchangeRate": "5.776073",
                "inverseRate": "0.173128",
                "inverseDescription": "1 Chilean Peso = 0.173128 Japanese Yen"
            },
            {
                "title": "1 JPY = 0.033042 XCD",
                "link": "http://www.floatrates.com/jpy/xcd/",
                "description": "1 Japanese Yen = 0.033042 East Caribbean Dollar",
                "pubDate": null,
                "baseCurrency": "JPY",
                "baseName": "Japanese Yen",
                "targetCurrency": "XCD",
                "targetName": "East Caribbean Dollar",
                "exchangeRate": "0.033042",
                "inverseRate": "30.264099",
                "inverseDescription": "1 East Caribbean Dollar = 30.264099 Japanese Yen"
            },
            {
                "title": "1 JPY = 0.021628 FJD",
                "link": "http://www.floatrates.com/jpy/fjd/",
                "description": "1 Japanese Yen = 0.021628 Fiji Dollar",
                "pubDate": null,
                "baseCurrency": "JPY",
                "baseName": "Japanese Yen",
                "targetCurrency": "FJD",
                "targetName": "Fiji Dollar",
                "exchangeRate": "0.021628",
                "inverseRate": "46.235644",
                "inverseDescription": "1 Fiji Dollar = 46.235644 Japanese Yen"
            },
            {
                "title": "1 JPY = 0.018604 GHS",
                "link": "http://www.floatrates.com/jpy/ghs/",
                "description": "1 Japanese Yen = 0.018604 Ghanaian Cedi",
                "pubDate": null,
                "baseCurrency": "JPY",
                "baseName": "Japanese Yen",
                "targetCurrency": "GHS",
                "targetName": "Ghanaian Cedi",
                "exchangeRate": "0.018604",
                "inverseRate": "53.752390",
                "inverseDescription": "1 Ghanaian Cedi = 53.752390 Japanese Yen"
            },
            {
                "title": "1 JPY = 0.097763 GTQ",
                "link": "http://www.floatrates.com/jpy/gtq/",
                "description": "1 Japanese Yen = 0.097763 Guatemalan Quetzal",
                "pubDate": null,
                "baseCurrency": "JPY",
                "baseName": "Japanese Yen",
                "targetCurrency": "GTQ",
                "targetName": "Guatemalan Quetzal",
                "exchangeRate": "0.097763",
                "inverseRate": "10.228806",
                "inverseDescription": "1 Guatemalan Quetzal = 10.228806 Japanese Yen"
            },
            {
                "title": "1 JPY = 0.233814 HNL",
                "link": "http://www.floatrates.com/jpy/hnl/",
                "description": "1 Japanese Yen = 0.233814 Honduran Lempira",
                "pubDate": null,
                "baseCurrency": "JPY",
                "baseName": "Japanese Yen",
                "targetCurrency": "HNL",
                "targetName": "Honduran Lempira",
                "exchangeRate": "0.233814",
                "inverseRate": "4.276901",
                "inverseDescription": "1 Honduran Lempira = 4.276901 Japanese Yen"
            },
            {
                "title": "1 JPY = 1.429498 ISK",
                "link": "http://www.floatrates.com/jpy/isk/",
                "description": "1 Japanese Yen = 1.429498 Icelandic Krona",
                "pubDate": null,
                "baseCurrency": "JPY",
                "baseName": "Japanese Yen",
                "targetCurrency": "ISK",
                "targetName": "Icelandic Krona",
                "exchangeRate": "1.429498",
                "inverseRate": "0.699546",
                "inverseDescription": "1 Icelandic Krona = 0.699546 Japanese Yen"
            },
            {
                "title": "1 JPY = 1.054410 JMD",
                "link": "http://www.floatrates.com/jpy/jmd/",
                "description": "1 Japanese Yen = 1.054410 Jamaican Dollar",
                "pubDate": null,
                "baseCurrency": "JPY",
                "baseName": "Japanese Yen",
                "targetCurrency": "JMD",
                "targetName": "Jamaican Dollar",
                "exchangeRate": "1.054410",
                "inverseRate": "0.948398",
                "inverseDescription": "1 Jamaican Dollar = 0.948398 Japanese Yen"
            },
            {
                "title": "1 JPY = 0.098081 MAD",
                "link": "http://www.floatrates.com/jpy/mad/",
                "description": "1 Japanese Yen = 0.098081 Moroccan Dirham",
                "pubDate": null,
                "baseCurrency": "JPY",
                "baseName": "Japanese Yen",
                "targetCurrency": "MAD",
                "targetName": "Moroccan Dirham",
                "exchangeRate": "0.098081",
                "inverseRate": "10.195663",
                "inverseDescription": "1 Moroccan Dirham = 10.195663 Japanese Yen"
            },
            {
                "title": "1 JPY = 0.066067 MMK",
                "link": "http://www.floatrates.com/jpy/mmk/",
                "description": "1 Japanese Yen = 0.066067 Myanma Kyat",
                "pubDate": null,
                "baseCurrency": "JPY",
                "baseName": "Japanese Yen",
                "targetCurrency": "MMK",
                "targetName": "Myanma Kyat",
                "exchangeRate": "0.066067",
                "inverseRate": "15.136201",
                "inverseDescription": "1 Myanma Kyat = 15.136201 Japanese Yen"
            },
            {
                "title": "1 JPY = 0.021655 ANG",
                "link": "http://www.floatrates.com/jpy/ang/",
                "description": "1 Japanese Yen = 0.021655 Neth. Antillean Guilder",
                "pubDate": null,
                "baseCurrency": "JPY",
                "baseName": "Japanese Yen",
                "targetCurrency": "ANG",
                "targetName": "Neth. Antillean Guilder",
                "exchangeRate": "0.021655",
                "inverseRate": "46.178885",
                "inverseDescription": "1 Neth. Antillean Guilder = 46.178885 Japanese Yen"
            },
            {
                "title": "1 JPY = 1.062756 PKR",
                "link": "http://www.floatrates.com/jpy/pkr/",
                "description": "1 Japanese Yen = 1.062756 Pakistani Rupee",
                "pubDate": null,
                "baseCurrency": "JPY",
                "baseName": "Japanese Yen",
                "targetCurrency": "PKR",
                "targetName": "Pakistani Rupee",
                "exchangeRate": "1.062756",
                "inverseRate": "0.940950",
                "inverseDescription": "1 Pakistani Rupee = 0.940950 Japanese Yen"
            },
            {
                "title": "1 JPY = 0.012375 PAB",
                "link": "http://www.floatrates.com/jpy/pab/",
                "description": "1 Japanese Yen = 0.012375 Panamanian Balboa",
                "pubDate": null,
                "baseCurrency": "JPY",
                "baseName": "Japanese Yen",
                "targetCurrency": "PAB",
                "targetName": "Panamanian Balboa",
                "exchangeRate": "0.012375",
                "inverseRate": "80.809666",
                "inverseDescription": "1 Panamanian Balboa = 80.809666 Japanese Yen"
            },
            {
                "title": "1 JPY = 0.034299 PEN",
                "link": "http://www.floatrates.com/jpy/pen/",
                "description": "1 Japanese Yen = 0.034299 Peruvian Nuevo Sol",
                "pubDate": null,
                "baseCurrency": "JPY",
                "baseName": "Japanese Yen",
                "targetCurrency": "PEN",
                "targetName": "Peruvian Nuevo Sol",
                "exchangeRate": "0.034299",
                "inverseRate": "29.155251",
                "inverseDescription": "1 Peruvian Nuevo Sol = 29.155251 Japanese Yen"
            },
            {
                "title": "1 JPY = 0.841473 RSD",
                "link": "http://www.floatrates.com/jpy/rsd/",
                "description": "1 Japanese Yen = 0.841473 Serbian Dinar",
                "pubDate": null,
                "baseCurrency": "JPY",
                "baseName": "Japanese Yen",
                "targetCurrency": "RSD",
                "targetName": "Serbian Dinar",
                "exchangeRate": "0.841473",
                "inverseRate": "1.188393",
                "inverseDescription": "1 Serbian Dinar = 1.188393 Japanese Yen"
            },
            {
                "title": "1 JPY = 1.358312 LKR",
                "link": "http://www.floatrates.com/jpy/lkr/",
                "description": "1 Japanese Yen = 1.358312 Sri Lanka Rupee",
                "pubDate": null,
                "baseCurrency": "JPY",
                "baseName": "Japanese Yen",
                "targetCurrency": "LKR",
                "targetName": "Sri Lanka Rupee",
                "exchangeRate": "1.358312",
                "inverseRate": "0.736208",
                "inverseDescription": "1 Sri Lanka Rupee = 0.736208 Japanese Yen"
            },
            {
                "title": "1 JPY = 0.079081 TTD",
                "link": "http://www.floatrates.com/jpy/ttd/",
                "description": "1 Japanese Yen = 0.079081 Trinidad Tobago Dollar",
                "pubDate": null,
                "baseCurrency": "JPY",
                "baseName": "Japanese Yen",
                "targetCurrency": "TTD",
                "targetName": "Trinidad Tobago Dollar",
                "exchangeRate": "0.079081",
                "inverseRate": "12.645302",
                "inverseDescription": "1 Trinidad Tobago Dollar = 12.645302 Japanese Yen"
            },
            {
                "title": "1 JPY = 0.017005 TND",
                "link": "http://www.floatrates.com/jpy/tnd/",
                "description": "1 Japanese Yen = 0.017005 Tunisian Dinar",
                "pubDate": null,
                "baseCurrency": "JPY",
                "baseName": "Japanese Yen",
                "targetCurrency": "TND",
                "targetName": "Tunisian Dinar",
                "exchangeRate": "0.017005",
                "inverseRate": "58.805641",
                "inverseDescription": "1 Tunisian Dinar = 58.805641 Japanese Yen"
            },
            {
                "title": "1 JPY = 0.053137 VEF",
                "link": "http://www.floatrates.com/jpy/vef/",
                "description": "1 Japanese Yen = 0.053137 Venezuelan Bolivar (till 20 August 2018)",
                "pubDate": null,
                "baseCurrency": "JPY",
                "baseName": "Japanese Yen",
                "targetCurrency": "VEF",
                "targetName": "Venezuelan Bolivar (till 20 August 2018)",
                "exchangeRate": "0.053137",
                "inverseRate": "18.819142",
                "inverseDescription": "1 Venezuelan Bolivar (till 20 August 2018) = 18.819142 Japanese Yen"
            },
            {
                "title": "1 JPY = 0.893980 DZD",
                "link": "http://www.floatrates.com/jpy/dzd/",
                "description": "1 Japanese Yen = 0.893980 Algerian Dinar",
                "pubDate": null,
                "baseCurrency": "JPY",
                "baseName": "Japanese Yen",
                "targetCurrency": "DZD",
                "targetName": "Algerian Dinar",
                "exchangeRate": "0.893980",
                "inverseRate": "1.118594",
                "inverseDescription": "1 Algerian Dinar = 1.118594 Japanese Yen"
            },
            {
                "title": "1 JPY = 0.081734 BWP",
                "link": "http://www.floatrates.com/jpy/bwp/",
                "description": "1 Japanese Yen = 0.081734 Botswana Pula",
                "pubDate": null,
                "baseCurrency": "JPY",
                "baseName": "Japanese Yen",
                "targetCurrency": "BWP",
                "targetName": "Botswana Pula",
                "exchangeRate": "0.081734",
                "inverseRate": "12.234865",
                "inverseDescription": "1 Botswana Pula = 12.234865 Japanese Yen"
            },
            {
                "title": "1 JPY = 0.015286 BND",
                "link": "http://www.floatrates.com/jpy/bnd/",
                "description": "1 Japanese Yen = 0.015286 Brunei Dollar",
                "pubDate": null,
                "baseCurrency": "JPY",
                "baseName": "Japanese Yen",
                "targetCurrency": "BND",
                "targetName": "Brunei Dollar",
                "exchangeRate": "0.015286",
                "inverseRate": "65.419415",
                "inverseDescription": "1 Brunei Dollar = 65.419415 Japanese Yen"
            },
            {
                "title": "1 JPY = 22.627235 COP",
                "link": "http://www.floatrates.com/jpy/cop/",
                "description": "1 Japanese Yen = 22.627235 Colombian Peso",
                "pubDate": null,
                "baseCurrency": "JPY",
                "baseName": "Japanese Yen",
                "targetCurrency": "COP",
                "targetName": "Colombian Peso",
                "exchangeRate": "22.627235",
                "inverseRate": "0.044195",
                "inverseDescription": "1 Colombian Peso = 0.044195 Japanese Yen"
            },
            {
                "title": "1 JPY = 1.795216 KZT",
                "link": "http://www.floatrates.com/jpy/kzt/",
                "description": "1 Japanese Yen = 1.795216 Kazakhstani Tenge",
                "pubDate": null,
                "baseCurrency": "JPY",
                "baseName": "Japanese Yen",
                "targetCurrency": "KZT",
                "targetName": "Kazakhstani Tenge",
                "exchangeRate": "1.795216",
                "inverseRate": "0.557036",
                "inverseDescription": "1 Kazakhstani Tenge = 0.557036 Japanese Yen"
            },
            {
                "title": "1 JPY = 0.003408 KWD",
                "link": "http://www.floatrates.com/jpy/kwd/",
                "description": "1 Japanese Yen = 0.003408 Kuwaiti Dinar",
                "pubDate": null,
                "baseCurrency": "JPY",
                "baseName": "Japanese Yen",
                "targetCurrency": "KWD",
                "targetName": "Kuwaiti Dinar",
                "exchangeRate": "0.003408",
                "inverseRate": "293.414149",
                "inverseDescription": "1 Kuwaiti Dinar = 293.414149 Japanese Yen"
            },
            {
                "title": "1 JPY = 0.023897 LYD",
                "link": "http://www.floatrates.com/jpy/lyd/",
                "description": "1 Japanese Yen = 0.023897 Libyan Dinar",
                "pubDate": null,
                "baseCurrency": "JPY",
                "baseName": "Japanese Yen",
                "targetCurrency": "LYD",
                "targetName": "Libyan Dinar",
                "exchangeRate": "0.023897",
                "inverseRate": "41.846895",
                "inverseDescription": "1 Libyan Dinar = 41.846895 Japanese Yen"
            },
            {
                "title": "1 JPY = 0.349558 MUR",
                "link": "http://www.floatrates.com/jpy/mur/",
                "description": "1 Japanese Yen = 0.349558 Mauritian Rupee",
                "pubDate": null,
                "baseCurrency": "JPY",
                "baseName": "Japanese Yen",
                "targetCurrency": "MUR",
                "targetName": "Mauritian Rupee",
                "exchangeRate": "0.349558",
                "inverseRate": "2.860754",
                "inverseDescription": "1 Mauritian Rupee = 2.860754 Japanese Yen"
            },
            {
                "title": "1 JPY = 0.895938 NPR",
                "link": "http://www.floatrates.com/jpy/npr/",
                "description": "1 Japanese Yen = 0.895938 Nepalese Rupee",
                "pubDate": null,
                "baseCurrency": "JPY",
                "baseName": "Japanese Yen",
                "targetCurrency": "NPR",
                "targetName": "Nepalese Rupee",
                "exchangeRate": "0.895938",
                "inverseRate": "1.116148",
                "inverseDescription": "1 Nepalese Rupee = 1.116148 Japanese Yen"
            },
            {
                "title": "1 JPY = 0.004755 OMR",
                "link": "http://www.floatrates.com/jpy/omr/",
                "description": "1 Japanese Yen = 0.004755 Omani Rial",
                "pubDate": null,
                "baseCurrency": "JPY",
                "baseName": "Japanese Yen",
                "targetCurrency": "OMR",
                "targetName": "Omani Rial",
                "exchangeRate": "0.004755",
                "inverseRate": "210.311936",
                "inverseDescription": "1 Omani Rial = 210.311936 Japanese Yen"
            },
            {
                "title": "1 JPY = 0.045013 QAR",
                "link": "http://www.floatrates.com/jpy/qar/",
                "description": "1 Japanese Yen = 0.045013 Qatari Rial",
                "pubDate": null,
                "baseCurrency": "JPY",
                "baseName": "Japanese Yen",
                "targetCurrency": "QAR",
                "targetName": "Qatari Rial",
                "exchangeRate": "0.045013",
                "inverseRate": "22.215643",
                "inverseDescription": "1 Qatari Rial = 22.215643 Japanese Yen"
            },
            {
                "title": "1 JPY = 0.046374 SAR",
                "link": "http://www.floatrates.com/jpy/sar/",
                "description": "1 Japanese Yen = 0.046374 Saudi Riyal",
                "pubDate": null,
                "baseCurrency": "JPY",
                "baseName": "Japanese Yen",
                "targetCurrency": "SAR",
                "targetName": "Saudi Riyal",
                "exchangeRate": "0.046374",
                "inverseRate": "21.563984",
                "inverseDescription": "1 Saudi Riyal = 21.563984 Japanese Yen"
            }
        ]
    }
}